its_hub/__init__.py
its_hub/_version.py
its_hub/base.py
its_hub/error_handling.py
its_hub/lms.py
its_hub/types.py
its_hub/utils.py
its_hub/algorithms/__init__.py
its_hub/algorithms/beam_search.py
its_hub/algorithms/bon.py
its_hub/algorithms/particle_gibbs.py
its_hub/algorithms/planning_wrapper.py
its_hub/algorithms/self_consistency.py
its_hub/integration/__init__.py
its_hub/integration/iaas.py
its_hub/integration/reward_hub.py
its_hub-0.3.4.dist-info/licenses/LICENSE
its_hub-0.3.4.dist-info/METADATA
its_hub-0.3.4.dist-info/WHEEL
its_hub-0.3.4.dist-info/entry_points.txt
its_hub-0.3.4.dist-info/top_level.txt
its_hub-0.3.4.dist-info/RECORD
