Metadata-Version: 2.4
Name: its_hub
Version: 0.3.4
Summary: A Python library for inference-time scaling LLMs
Author-email: Kai Xu and the Red Hat AI Innovation Team <xuk@redhat.com>
License-Expression: Apache-2.0
Project-URL: Homepage, https://ai-innovation.team/its_hub
Classifier: Programming Language :: Python :: 3
Classifier: Programming Language :: Python :: 3.11
Classifier: Programming Language :: Python :: 3.12
Classifier: Operating System :: OS Independent
Classifier: Topic :: Scientific/Engineering :: Artificial Intelligence
Requires-Python: >=3.10
License-File: LICENSE
Requires-Dist: openai>=1.68.2
Requires-Dist: tqdm>=4.65.0
Requires-Dist: typing-extensions>=4.12.2
Requires-Dist: reward-hub>=0.1.7
Requires-Dist: transformers>=4.53.2
Requires-Dist: backoff>=2.2.0
Requires-Dist: click>=8.1.0
Requires-Dist: fastapi>=0.115.5
Requires-Dist: pydantic>=2.7.2
Requires-Dist: numpy
Requires-Dist: uvicorn
Requires-Dist: requests
Requires-Dist: aiohttp>=3.9.0
Requires-Dist: litellm<1.75.0,>=1.70.0
Provides-Extra: vllm
Requires-Dist: reward-hub[vllm]>=0.1.6; extra == "vllm"
Provides-Extra: dev
Requires-Dist: pytest>=7.0.0; extra == "dev"
Requires-Dist: pytest-asyncio>=0.21.0; extra == "dev"
Requires-Dist: pytest-cov>=4.1.0; extra == "dev"
Requires-Dist: ruff>=0.10.0; extra == "dev"
Requires-Dist: jupytext>=1.15.0; extra == "dev"
Requires-Dist: jupyter>=1.0.0; extra == "dev"
Requires-Dist: reward-hub[vllm]>=0.1.6; extra == "dev"
Provides-Extra: prm
Requires-Dist: reward-hub[prm]>=0.1.6; extra == "prm"
Provides-Extra: research
Requires-Dist: math-verify>=0.1.0; extra == "research"
Requires-Dist: datasets>=2.0.0; extra == "research"
Requires-Dist: matplotlib>=3.5.0; extra == "research"
Provides-Extra: cloud
Requires-Dist: boto3>=1.28.0; extra == "cloud"
Requires-Dist: google-cloud-aiplatform>=1.38.0; extra == "cloud"
Dynamic: license-file
